{
  "generator_info": "Shape definitions generated with PhysicsEditor. Visit https://www.codeandweb.com/physicseditor",
  "KADOS_00000": {
    "type": "fromPhysicsEditor",
    "label": "KADOS_00000",
    "isStatic": false,
    "density": 0.1,
    "restitution": 0,
    "friction": 0.1,
    "frictionAir": 0.01,
    "frictionStatic": 0.5,
    "collisionFilter": {
      "group": 0,
      "category": 1,
      "mask": 255
    },
    "fixtures": [
      {
        "label": "kados",
        "isSensor": false,
        "vertices": [
          [
            { "x": 155, "y": 110 },
            { "x": 132, "y": 136 },
            { "x": 165, "y": 133 }
          ],
          [
            { "x": 196, "y": 112 },
            { "x": 165, "y": 133 },
            { "x": 197, "y": 170 }
          ],
          [
            { "x": 206, "y": 165 },
            { "x": 197, "y": 170 },
            { "x": 211, "y": 185 }
          ],
          [
            { "x": 122, "y": 129 },
            { "x": 113, "y": 133 },
            { "x": 132, "y": 136 }
          ],
          [
            { "x": 70, "y": 238 },
            { "x": 257, "y": 238 },
            { "x": 228, "y": 218 },
            { "x": 62, "y": 152 },
            { "x": 51, "y": 154 }
          ],
          [
            { "x": 165, "y": 133 },
            { "x": 132, "y": 136 },
            { "x": 62, "y": 152 },
            { "x": 228, "y": 218 },
            { "x": 197, "y": 170 }
          ],
          [
            { "x": 224, "y": 194 },
            { "x": 211, "y": 185 },
            { "x": 228, "y": 218 }
          ],
          [
            { "x": 110, "y": 125 },
            { "x": 87, "y": 125 },
            { "x": 62, "y": 142 },
            { "x": 62, "y": 152 },
            { "x": 113, "y": 133 }
          ],
          [
            { "x": 113, "y": 133 },
            { "x": 62, "y": 152 },
            { "x": 132, "y": 136 }
          ],
          [
            { "x": 211, "y": 185 },
            { "x": 197, "y": 170 },
            { "x": 228, "y": 218 }
          ]
        ]
      }
    ]
  }
}
